Workbook

Sheet Overview
A1: Georgian translation
A3: Fill in the GEORGIAN column (shaded) on each tab. Leave key, english and source alone.
A4: Rows still to do are sorted to the top of every tab. Green means already translated.
A6: Example of a finished row, from the wallet tab:
A7: key savedCardsPanel.savedCards
A8: english Saved cards
A9: georgian შენახული ბარათები
A11: Keep {placeholders} in braces exactly as they are — word order around them can change.
A12: Do not translate: the brand name, IDs, licence plates, ₾, API, SMS.
A13: Formal address (თქვენ). Buttons are verbal nouns — შენახვა, not შეინახე.
A14: Read src/messages/GLOSSARY.md before starting: it settles Order / Load / Job / Cargo,
A15: which are four different words in Georgian and must stay different.
A17: When done, save this file and run: python3 scripts/translations_xlsx.py --merge
A19: Tab | B19: Strings | C19: Done | D19: Remaining
A20: account | B20: 18 | C20: =COUNTA('account'!C2:C19) | D20: =B20-C20
A21: admin | B21: 825 | C21: =COUNTA('admin'!C2:C826) | D21: =B21-C21
A22: auth | B22: 96 | C22: =COUNTA('auth'!C2:C97) | D22: =B22-C22
A23: checkout | B23: 47 | C23: =COUNTA('checkout'!C2:C48) | D23: =B23-C23
A24: cities | B24: 74 | C24: =COUNTA('cities'!C2:C75) | D24: =B24-C24
A25: cityLanding | B25: 234 | C25: =COUNTA('cityLanding'!C2:C235) | D25: =B25-C25
A26: common | B26: 385 | C26: =COUNTA('common'!C2:C386) | D26: =B26-C26
A27: dashboard | B27: 106 | C27: =COUNTA('dashboard'!C2:C107) | D27: =B27-C27
A28: driverHub | B28: 629 | C28: =COUNTA('driverHub'!C2:C630) | D28: =B28-C28
A29: errors | B29: 431 | C29: =COUNTA('errors'!C2:C432) | D29: =B29-C29
A30: fleet | B30: 213 | C30: =COUNTA('fleet'!C2:C214) | D30: =B30-C30
A31: home | B31: 151 | C31: =COUNTA('home'!C2:C152) | D31: =B31-C31
A32: landing | B32: 26 | C32: =COUNTA('landing'!C2:C27) | D32: =B32-C32
A33: onboarding | B33: 215 | C33: =COUNTA('onboarding'!C2:C216) | D33: =B33-C33
A34: orders | B34: 24 | C34: =COUNTA('orders'!C2:C25) | D34: =B34-C34
A35: wallet | B35: 20 | C35: =COUNTA('wallet'!C2:C21) | D35: =B35-C35
A36: TOTAL | B36: =SUM(B20:B35) | C36: =SUM(C20:C35) | D36: =SUM(D20:D35)

Sheet account
A1: key | B1: english | C1: georgian | D1: source
A2: account.pleaseSignInToViewYour | B2: Please sign in to view your account. | C2: თხოვთ გაიაროთ ავტორიზაცია თქვენი ანგარიშის სანახავად | D2: src/app/[locale]/account/page.tsx
A3: account.settings | B3: Settings | C3: პარამეტრები | D3: src/app/[locale]/account/page.tsx
A4: account.theDetailsADriverSeesWhen | B4: The details a driver sees when they turn up for one of your pickups, and the credentials you sign in with. Keeping your phone number current is what stops a delivery stalling at the kerb. | C4: დეტალები, რომლებსაც მძღოლი ხედავს, როდესაც ის თქვენთან ტვირთის ასაღებად მოდის, და მონაცემები, რომლებითაც შედიხართ სისტემაში. ტელეფონის ნომრის განახლებულ მდგომარეობაში შენარჩუნება თავიდან აგარიდებთ მიწოდების შეფერხებას. | D4: src/app/[locale]/account/page.tsx
A5: accountPasswordCard.changePassword | B5: Change password | C5: პაროლის შეცვლა | D5: src/components/account-password-card.tsx
A6: accountPasswordCard.couldNotChangePassword | B6: Could not change your password. Please try again. | C6: პაროლის შეცვლა ვერ მოხერხდა. გთხოვთ, სცადოთ ხელახლა. | D6: src/components/account-password-card.tsx
A7: accountPasswordCard.savePassword | B7: Save password | C7: პაროლის შენახვა | D7: src/components/account-password-card.tsx
A8: accountProfileForm.businessDescription | B8: Who the delivery is billed to, and how a driver reaches you about a pickup. | C8: ვის ეკისრება მიწოდების ანგარიში და როგორ დაგიკავშირდებათ მძღოლი აღებასთან დაკავშირებით. | D8: src/components/account-profile-form.tsx
A9: accountProfileForm.couldNotSaveProfile | B9: Could not save your profile. Please try again. | C9: პროფილის შენახვა ვერ მოხერხდა. გთხოვთ, სცადოთ ხელახლა. | D9: src/components/account-profile-form.tsx
A10: accountProfileForm.female | B10: Female | C10: მდედრობითი | D10: src/components/account-profile-form.tsx
A11: accountProfileForm.gender | B11: Gender | C11: სქემი | D11: src/components/account-profile-form.tsx
A12: accountProfileForm.individualDescription | B12: How a driver identifies and reaches you when they arrive for a pickup. | C12: როგორ გიცნობთ და დაგიკავშირდებათ მძღოლი, როცა აღებაზე მოვა. | D12: src/components/account-profile-form.tsx
... A19: accountSidebar.loggingOut | B19: Logging out… | C19: გასვლა… | D19: src/components/account-sidebar.tsx

Sheet admin
A1: key | B1: english | C1: georgian | D1: source
A2: adminBusinessApplications.applicationCount | B2: {count, plural, one {# application} other {# applications}} | C2: {count, plural, one {# განაცხადი} other {# განაცხადი}} | D2: src/app/[locale]/admin/(sections)/business/applications/page.tsx
A3: adminBusinessApplications.companyFlagged | B3: Company flagged | C3: კომპანია მონიშნულია | D3: src/app/[locale]/admin/(sections)/business/applications/page.tsx
A4: adminBusinessApplications.companyUnverified | B4: Company unverified | C4: კომპანია არ არის დადასტურებული | D4: src/app/[locale]/admin/(sections)/business/applications/page.tsx
A5: adminBusinessApplications.couldNotLoadFleetApplications | B5: Could not load fleet applications. | C5: ვტოპარკის განაცხადების ჩატვირთვა ვერ მოხერხდა | D5: src/app/[locale]/admin/(sections)/business/applications/page.tsx
A6: adminBusinessApplications.emptyActionRequired | B6: No action-required fleet applications. | C6: ქმედების მომთხოვნი ავტოპარკის განაცხადები არ არის. | D6: src/app/[locale]/admin/(sections)/business/applications/page.tsx
A7: adminBusinessApplications.emptyAll | B7: No fleet applications yet. | C7: ავტოპარკის განაცხადები ჯერ არ არის. | D7: src/app/[locale]/admin/(sections)/business/applications/page.tsx
A8: adminBusinessApplications.emptyApproved | B8: No activated fleets. | C8: აქტიური ავტოპარკები არ არის. | D8: src/app/[locale]/admin/(sections)/business/applications/page.tsx
A9: adminBusinessApplications.emptyPending | B9: No pending fleet applications. | C9: განხილვაში მყოფი ავტოპარკის განაცხადები არ არის. | D9: src/app/[locale]/admin/(sections)/business/applications/page.tsx
A10: adminBusinessApplications.fleetActive | B10: Fleet active | C10: ავტოპარკი აქტიურია | D10: src/app/[locale]/admin/(sections)/business/applications/page.tsx
A11: adminBusinessApplications.loadingFleetApplications | B11: Loading fleet applications… | C11: ავტოპარკის განაცხადები იტვირთება... | D11: src/app/[locale]/admin/(sections)/business/applications/page.tsx
A12: adminChangePasswordForm.yourBackOfficeAccountWasCreated | B12: Your back-office account was created with a temporary password. Choose a new one to continue. | C12: თქვენი ადმინისტრაციული ანგარიში შეიქმნა დროებითი პაროლით. გაგრძელებისთვის აირჩიეთ ახალი პაროლი. | D12: src/components/admin/admin-change-password-form.tsx
... A826: translationFormDialog.newTranslationKey | B826: New translation key | C826: თარგმანის ახალი გასაღები | D826: src/components/admin/content/translation-form-dialog.tsx

Sheet auth
A1: key | B1: english | C1: georgian | D1: source
A2: accountTypeStep.step2Of3Type | B2: Step 2 of 3 · Type | C2: ნაბიჯი 2/3 · ტიპი | D2: src/components/auth/account-type-step.tsx
A3: accountTypeStep.thisDecidesWhatWeAskFor | B3: This decides what we ask for next — personal details or company documents. | C3: ს განსაზღვრავს, რას მოგთხოვთ შემდეგ ეტაპზე — პირად მონაცემებს თუ კომპანიის დოკუმენტებს. | D3: src/components/auth/account-type-step.tsx
A4: accountTypeStep.whichDescribesYou | B4: Which describes you? | C4: რომელი შეგესაბამებათ უკეთ? | D4: src/components/auth/account-type-step.tsx
A5: auth.accountsCannotBeCreatedFromThe | B5: Accounts cannot be created from the admin host. | C5: ადმინისტრაციული ჰოსტიდან ანგარიშების შექმნა შეუძლებელია. | D5: src/lib/auth.ts
A6: auth.adminAccountsCannotBeCreatedThrough | B6: Admin accounts cannot be created through sign-up. | C6: ადმინისტრატორის ანგარიშების შექმნა რეგისტრაციის ფორმით შეუძლებელია. | D6: src/lib/auth.ts
A7: auth.clientAccountsMustBeCreatedFrom | B7: Client accounts must be created from the main sign-up page. | C7: კლიენტის ანგარიშები უნდა შეიქმნას რეგისტრაციის მთავარი გვერდიდან. | D7: src/lib/auth.ts
A8: auth.driverAndLogisticsCompanyAccountsMust | B8: Driver and logistics company accounts must be created from the merchant sign-up page. | C8: მძღოლისა და ლოჯისტიკური კომპანიის ანგარიშები უნდა შეიქმნას პარტნიორის რეგისტრაციის გვერდიდან. | D8: src/lib/auth.ts
A9: authFlow.aPrivatePersonNoRegistrationNumber | B9: A private person, no registration number | C9: ფიზიკური პირი, საიდენტიფიკაციო კოდის გარეშე | D9: src/lib/auth-flow.ts
A10: authFlow.aRegisteredCompanyWithAVat | B10: A registered company with a VAT ID | C10: რეგისტრირებული კომპანია დღგ-ის გადამხდელის ნომრით | D10: src/lib/auth-flow.ts
A11: authFlow.bookDeliveriesForYourPackages | B11: Book deliveries for your packages | C11: შეუკვეთეთ მიწოდება თქვენი ამანათებისთვის | D11: src/lib/auth-flow.ts
A12: authFlow.clientBenefitInstantQuote | B12: Instant price quote before you book | C12: მყისიერი წინასწარი ფასი დაჯავშნამდე | D12: src/lib/auth-flow.ts
... A97: signUpSuccess.yourAccountHasBeenCreated | B97: Your account has been created. | C97: თქვენი ანგარიში წარმატებით შეიქმნა. | D97: src/components/auth/sign-up-success.tsx

Sheet checkout
A1: key | B1: english | C1: georgian | D1: source
A2: bodyType.dryBox | B2: Dry box | C2: მშრალი ფურგონი | D2: src/app/[locale]/checkout/checkout-format.ts
A3: bodyType.openChassis | B3: Open chassis | C3: ღია პლატფორმა | D3: src/app/[locale]/checkout/checkout-format.ts
A4: bodyType.refrigerated | B4: Refrigerated | C4: მაცივარ-ფურგონი | D4: src/app/[locale]/checkout/checkout-format.ts
A5: checkout.almostThere | B5: Almost there | C5: თითქმის მზადაა | D5: src/app/[locale]/checkout/[id]/page.tsx
A6: checkout.backToBooking | B6: ← Back to booking | C6: ← დაჯავშნაზე დაბრუნება | D6: src/app/[locale]/checkout/[id]/page.tsx
A7: checkout.crew | B7: Crew | C7: დამხმარე პერსონალი | D7: src/app/[locale]/checkout/[id]/page.tsx
A8: checkout.goods | B8: Goods | C8: ტვირთი | D8: src/app/[locale]/checkout/[id]/page.tsx
A9: checkout.loadSpace | B9: Load space | C9: სატვირთო სივრცე | D9: src/app/[locale]/checkout/[id]/page.tsx
A10: checkout.loadingAndUnloadingTimeBeyondThe | B10: Loading and unloading time beyond the free allowance is settled after the delivery and is not part of this total. | C10: უფასო ლიმიტს გადაცილებული დატვირთვა-დაცლის დროის საფასური გადაიხდება მიწოდების შემდეგ და არ შედის ამ ჯამურ თანხაში. | D10: src/app/[locale]/checkout/[id]/page.tsx
A11: checkout.notes | B11: Notes | C11: შენიშვნები | D11: src/app/[locale]/checkout/[id]/page.tsx
A12: checkout.reviewAndPay | B12: Review and pay | C12: გადამოწმება და გადახდა | D12: src/app/[locale]/checkout/[id]/page.tsx
... A48: paymentMethod.cash | B48: Pay later | C48: მოგვიანებით გადახდა | D48: src/app/[locale]/checkout/checkout-format.ts

Sheet cities
A1: key | B1: english | C1: georgian | D1: source
A2: georgianCities.abasha | B2: Abasha | C2: აბაშა | D2: src/lib/georgian-cities.ts
A3: georgianCities.adigeni | B3: Adigeni | C3: ადიგენი | D3: src/lib/georgian-cities.ts
A4: georgianCities.adjara | B4: Adjara | C4: აჭარა | D4: src/lib/georgian-cities.ts
A5: georgianCities.akhalkalaki | B5: Akhalkalaki | C5: ახალქალაქი | D5: src/lib/georgian-cities.ts
A6: georgianCities.akhaltsikhe | B6: Akhaltsikhe | C6: ახალციხე | D6: src/lib/admin/home-page-content.ts
A7: georgianCities.akhmeta | B7: Akhmeta | C7: ახმეტა | D7: src/lib/georgian-cities.ts
A8: georgianCities.ambrolauri | B8: Ambrolauri | C8: ამბროლაური | D8: src/lib/georgian-cities.ts
A9: georgianCities.aspindza | B9: Aspindza | C9: ასპინძა | D9: src/lib/georgian-cities.ts
A10: georgianCities.baghdati | B10: Baghdati | C10: ბაღდათი | D10: src/lib/georgian-cities.ts
A11: georgianCities.batumi | B11: Batumi | C11: ბათუმი | D11: src/lib/admin/home-page-content.ts
A12: georgianCities.bolnisi | B12: Bolnisi | C12: ბოლნისი | D12: src/lib/georgian-cities.ts
... A75: georgianCities.zugdidi | B75: Zugdidi | C75: ზუგდიდი | D75: src/lib/admin/home-page-content.ts

Sheet cityLanding
A1: key | B1: english | C1: georgian | D1: source
A2: cities.batumi.areas.body | B2: The service area runs along the coast from Makhinjauri in the north to Gonio in the south, including: | C2: მომსახურების არეალი სანაპიროს გასწვრივ ვრცელდება — ჩრდილოეთით მახინჯაურიდან სამხრეთით გონიომდე, მათ შორის: | D2: src/components/city-landing/city-landing-page.tsx
A3: cities.batumi.areas.heading | B3: From the port to Gonio | C3: პორტიდან გონიომდე | D3: src/components/city-landing/city-landing-page.tsx
A4: cities.batumi.areas.list.a1 | B4: Port area | C4: პორტის მიმდებარე ტერიტორია | D4: src/components/city-landing/city-landing-page.tsx
A5: cities.batumi.areas.list.a2 | B5: Old Batumi and Europe Square | C5: ძველი ბათუმი და ევროპის მოედანი | D5: src/components/city-landing/city-landing-page.tsx
A6: cities.batumi.areas.list.a3 | B6: Old and New Boulevard | C6: ძველი და ახალი ბულვარი | D6: src/components/city-landing/city-landing-page.tsx
A7: cities.batumi.areas.list.a4 | B7: Tamar settlement | C7: თამარის დასახლება | D7: src/components/city-landing/city-landing-page.tsx
A8: cities.batumi.areas.list.a5 | B8: Makhinjauri | C8: მახინჯაური | D8: src/components/city-landing/city-landing-page.tsx
A9: cities.batumi.areas.list.a6 | B9: Gonio | C9: გონიო | D9: src/components/city-landing/city-landing-page.tsx
A10: cities.batumi.closing.heading | B10: Cargo to move in Batumi? | C10: ბათუმში ტვირთი გაქვთ გადასაზიდი? | D10: src/components/city-landing/city-landing-page.tsx
A11: cities.batumi.faq.heading | B11: Cargo delivery in Batumi: questions | C11: ტვირთის გადაზიდვა ბათუმში — კითხვები | D11: src/components/city-landing/city-landing-page.tsx
A12: cities.batumi.faq.intro | B12: Common questions about sending cargo in Batumi and along the Adjara coast. | C12: ხშირი კითხვები ბათუმსა და აჭარის სანაპიროზე ტვირთის გაგზავნის შესახებ. | D12: src/components/city-landing/city-landing-page.tsx
... A235: shared.otherCities.heading | B235: Cargo delivery across Georgia | C235: ტვირთის გადაზიდვა მთელ საქართველოში | D235: src/components/city-landing/city-landing-page.tsx

Sheet common
A1: key | B1: english | C1: georgian | D1: source
A2: addressAutocomplete.loadingAddressDetails | B2: Loading address details… | C2: მისამართის დეტალები იტვირთება... | D2: src/components/address-autocomplete.tsx
A3: addressAutocomplete.selectedAddress | B3: Selected address | C3: არჩეული მისამართი | D3: src/components/address-autocomplete.tsx
A4: authStatus.placeOrder | B4: Place order | C4: შეკვეთის განთავსება | D4: src/components/auth-status.tsx
A5: authStatus.signOut | B5: Sign out | C5: გასვლა | D5: src/components/auth-status.tsx
A6: authStatus.signingOut | B6: Signing out… | C6: გასვლა… | D6: src/components/auth-status.tsx
A7: cargoCategory.appliances | B7: Home & Office Appliances | C7: საყოფაცხოვრებო და საოფისე ტექნიკა | D7: src/lib/cargo.ts
A8: cargoCategory.constructionMaterials | B8: Construction & Hardware Materials | C8: სამშენებლო და სამეურნეო მასალები | D8: src/lib/cargo.ts
A9: cargoCategory.eventEquipment | B9: Event & Exhibition Equipment | C9: ღონისძიებებისა და გამოფენის აღჭურვილობა | D9: src/lib/cargo.ts
A10: cargoCategory.fullRelocation | B10: Full Relocation | C10: სრული გადასახლება | D10: src/lib/cargo.ts
A11: cargoCategory.furnitureFurnishings | B11: Furniture & Furnishings | C11: ავეჯი და ინტერიერის ნივთები | D11: src/lib/cargo.ts
A12: cargoCategory.industrialSupplies | B12: Industrial & Commercial Supplies | C12: სამრეწველო და კომერციული მასალები | D12: src/lib/cargo.ts
... A386: vehicleTypeSpecs.trailerTruck | B386: Trailer Truck | C386: მისაბმელიანი სატვირთო | D386: src/lib/vehicle-type-spec-labels.ts

Sheet dashboard
A1: key | B1: english | C1: georgian | D1: source
A2: dashboard.driverProfileNotSetUpFinishSigningUp | B2: Your driver profile isn't set up yet. Finish signing up as a driver to see your dashboard. | C2: თქვენი მძღოლის პროფილი ჯერ არ არის შექმნილი. დაასრულეთ რეგისტრაცია მძღოლად, რომ ნახოთ თქვენი დაფა. | D2: src/app/[locale]/dashboard/(hub)/layout.tsx
A3: dashboard.providerAccount | B3: Provider account | C3: პროვაიდერის ანგარიში | D3: src/app/[locale]/dashboard/(hub)/layout.tsx
A4: dashboardAccount.accountDriverHub | B4: Account · Driver Hub | C4: ანგარიში · მძღოლის ჰაბი | D4: src/app/[locale]/dashboard/(hub)/account/page.tsx
A5: dashboardDrivers.driversDriverHub | B5: Drivers · Driver Hub | C5: მძღოლები · მძღოლის ჰაბი | D5: src/app/[locale]/dashboard/(hub)/drivers/page.tsx
A6: dashboardEmployees.employeesRolesDriverHub | B6: Employees & roles · Driver Hub | C6: თანამშრომლები და როლები · მძღოლის ჰაბი | D6: src/app/[locale]/dashboard/(hub)/employees/page.tsx
A7: dashboardJobs.jobHistoryDriverHub | B7: Job history · Driver Hub | C7: შეკვეთების ისტორია · მძღოლის ჰაბი | D7: src/app/[locale]/dashboard/(hub)/jobs/page.tsx
A8: dashboardJobs.jobSheetDriverHub | B8: Job sheet · Driver Hub | C8: შეკვეთის ფურცელი · მძღოლის ჰაბი | D8: src/app/[locale]/dashboard/(hub)/jobs/[id]/page.tsx
A9: dashboardLoads.dashboardDriverHub | B9: Dashboard · Driver Hub | C9: მართვის პანელი · მძღოლის ჰაბი | D9: src/app/[locale]/dashboard/(hub)/loads/page.tsx
A10: dashboardPerformance.performanceDriverHub | B10: Performance · Driver Hub | C10: პროდუქტიულობა · მძღოლის ჰაბი | D10: src/app/[locale]/dashboard/(hub)/performance/page.tsx
A11: dashboardVehicles.vehiclesDriverHub | B11: Vehicles · Driver Hub | C11: ტრანსპორტი · მძღოლის ჰაბი | D11: src/app/[locale]/dashboard/(hub)/vehicles/page.tsx
A12: earnings.formerDriver | B12: Former driver | C12: ყოფილი მძღოლი | D12: src/lib/dashboard/hub/earnings.ts
... A107: sample.zurabMaisuradze | B107: Zurab Maisuradze | C107: ზურაბ მაისურაძე | D107: src/lib/dashboard/hub/sample.ts

Sheet driverHub
A1: key | B1: english | C1: georgian | D1: source
A2: driversAddPanel.articulatedCombinations | B2: Articulated combinations | D2: src/components/driver-hub/screens/drivers-add-panel.tsx
A3: driverAccountCompanyCard.companyDetailsNote | B3: Your registered details are the ones operations verified when your fleet was approved. They are corrected through the fleet application, so a change is re-checked rather than taking effect unseen — contact support to reopen it. | C3: თქვენი რეგისტრირებული მონაცემები ისაა, რომლებიც ოპერაციების გუნდმა გადაამოწმა ავტოპარკის დამტკიცებისას. ისინი ავტოპარკის განაცხადის მეშვეობით სწორდება, რათა ცვლილება ხელახლა შემოწმდეს და შეუმჩნევლად არ ამოქმედდეს — განაცხადის ხელახლა გასახსნელად დაუკავშირდით მხარდაჭერას. | D3: src/components/driver-hub/driver-account-company-card.tsx
A4: driverAccountCompanyCard.contactEmail | B4: Contact email | C4: საკონტაქტო ელფოსტა | D4: src/components/driver-hub/driver-account-company-card.tsx
A5: driverAccountCompanyCard.contactName | B5: Contact name | C5: საკონტაქტო პირის სახელი | D5: src/components/driver-hub/driver-account-company-card.tsx
A6: driverAccountCompanyCard.contactRole | B6: Contact role | C6: საკონტაქტო პირის როლი | D6: src/components/driver-hub/driver-account-company-card.tsx
A7: driverAccountCompanyCard.theAddressYouSignInWith | B7: The address you sign in with. | C7: მისამართი, რომლითაც შედიხართ სისტემაში. | D7: src/components/driver-hub/driver-account-company-card.tsx
A8: driverAccountCompanyCard.whatAClientIsBilledBy | B8: What a client is billed by, and how operations reaches your fleet. | C8: რით იბეგრება კლიენტი და როგორ უკავშირდება ოპერაციების გუნდი თქვენს ავტოპარკს. | D8: src/components/driver-hub/driver-account-company-card.tsx
A9: driverAccountPayoutPanel.accountYourFleetRegistered | B9: The account your fleet registered. | C9: თქვენი ავტოპარკის მიერ რეგისტრირებული ანგარიში. | D9: src/components/driver-hub/driver-account-payout-panel.tsx
A10: driverAccountPayoutPanel.bank | B10: Bank | C10: ბანკი | D10: src/components/driver-hub/driver-account-payout-panel.tsx
A11: driverAccountPayoutPanel.changeNote | B11: A payout account is changed through support so the new account can be verified against your registered details before any money moves. | C11: ანაზღაურების ანგარიში მხარდაჭერის მეშვეობით იცვლება, რათა ახალი ანგარიში თქვენს რეგისტრირებულ მონაცემებთან გადამოწმდეს, სანამ თანხა გადაირიცხება. | D11: src/components/driver-hub/driver-account-payout-panel.tsx
A12: driverAccountPayoutPanel.frequency | B12: Frequency | C12: სიხშირე | D12: src/components/driver-hub/driver-account-payout-panel.tsx
A13: driverAccountPayoutPanel.howOftenCompletedJobsAreSettled | B13: How often completed jobs are settled. | C13: რამდენად ხშირად ხდება დასრულებული შეკვეთების ანგარიშსწორება. | D13: src/components/driver-hub/driver-account-payout-panel.tsx
A14: driverAccountPayoutPanel.iban | B14: IBAN | C14: IBAN (ანგარიშის ნომერი) | D14: src/components/driver-hub/driver-account-payout-panel.tsx
... A630: vehiclesScreen.subtitleRoster | B630: {count, plural, one {# vehicle assigned to you} other {# vehicles assigned to you}} | C630: {count, plural, other {თქვენზე მიმაგრებულია # ავტომობილი}} | D630: src/components/driver-hub/screens/vehicles-screen.tsx

Sheet errors
A1: key | B1: english | C1: georgian | D1: source
A2: adminBusinessApplicationsActivate.atLeastOneVehicleMustBe | B2: At least one vehicle must be approved before activating the fleet. | C2: ავტოპარკის გააქტიურებამდე სავალდებულოა მინიმუმ ერთი ტრანსპორტის დადასტურება. | D2: src/app/api/admin/business-applications/[id]/activate/route.ts
A3: adminBusinessApplicationsActivate.thisApplicationIsStillWaitingOn | B3: This application is still waiting on the company to resubmit. | C3: ეს განაცხადი ჯერ კიდევ ელოდება კომპანიის მიერ ხელახლა გაგზავნას. | D3: src/app/api/admin/business-applications/[id]/activate/route.ts
A4: adminBusinessApplicationsActivate.vehiclesStillPendingReview | B4: {count, plural, one {# vehicle is still pending review.} other {# vehicles are still pending review.}} Decide every vehicle before activating the fleet. | C4: {count, plural, one {# ავტომობილი ჯერ კიდევ განხილვაშია.} other {# ავტომობილი ჯერ კიდევ განხილვაშია.}} ავტოპარკის გააქტიურებამდე მიიღეთ გადაწყვეტილება ყველა ავტომობილზე. | D4: src/app/api/admin/business-applications/[id]/activate/route.ts
A5: adminBusinessApplicationsActivate.verifyTheCompanySDetailsBefore | B5: Verify the company's details before activating the fleet. | C5: ავტოპარკის გააქტიურებამდე შეამოწმეთ კომპანიის მონაცემები. | D5: src/app/api/admin/business-applications/[id]/activate/route.ts
A6: adminBusinessApplicationsCompany.aReasonIsRequiredToFlag | B6: A reason is required to flag the company's details. | C6: კომპანიის მონაცემების მონიშვნისთვის აუცილებელია მიზეზის მითითება. | D6: src/app/api/admin/business-applications/[id]/company/route.ts
A7: adminBusinessApplicationsCompany.thatIsNotOneOfThe | B7: That is not one of the company flag reasons. | C7: ეს არ არის კომპანიის მონიშვნის მიზეზებიდან ერთ-ერთი. | D7: src/app/api/admin/business-applications/[id]/company/route.ts
A8: adminBusinessApplicationsCompany.verdictMustBeVerifiedOrFlagged | B8: verdict must be either "VERIFIED" or "FLAGGED". | C8: verdict უნდა იყოს "VERIFIED" ან "FLAGGED". | D8: src/app/api/admin/business-applications/[id]/company/route.ts
A9: adminBusinessApplicationsRequestChanges.changesHaveAlreadyBeenRequestedOn | B9: Changes have already been requested on this application. | C9: ამ განაცხადზე ცვლილებები უკვე მოთხოვნილია. | D9: src/app/api/admin/business-applications/[id]/request-changes/route.ts
A10: adminBusinessApplicationsRequestChanges.flagTheCompanySDetailsOr | B10: Flag the company's details or at least one vehicle before requesting changes. | C10: ცვლილებების მოთხოვნამდე მონიშნეთ კომპანიის მონაცემები ან მინიმუმ ერთი ტრანსპორტი. | D10: src/app/api/admin/business-applications/[id]/request-changes/route.ts
A11: adminBusinessApplicationsVehicles.aReasonIsRequiredToFlag | B11: A reason is required to flag a vehicle. | C11: ტრანსპორტის მონიშვნისთვის აუცილებელია მიზეზის მითითება. | D11: src/app/api/admin/business-applications/[id]/vehicles/[vehicleId]/route.ts
A12: adminBusinessApplicationsVehicles.thatIsNotOneOfThe | B12: That is not one of the vehicle flag reasons. | C12: ეს არ არის ტრანსპორტის მონიშვნის მიზეზებიდან ერთ-ერთი. | D12: src/app/api/admin/business-applications/[id]/vehicles/[vehicleId]/route.ts
... A432: wallet.unknownCursor | B432: cursor is not valid. | C432: cursor არასწორია. | D432: src/lib/mobile-api/wallet-api.ts

Sheet fleet
A1: key | B1: english | C1: georgian | D1: source
A2: fleetApplicationStatusScreen.actionRequiredBody | B2: The rest of the fleet is unaffected and stays in review. Fix what is flagged below and resubmit — approved vehicles keep their verdict. | C2: ავტოპარკის დანარჩენ ნაწილზე ეს გავლენას არ ახდენს და ის განხილვაში რჩება. გამოასწორეთ ქვემოთ მონიშნული და ხელახლა გაგზავნეთ — დამტკიცებული ავტომობილები თავის გადაწყვეტილებას ინარჩუნებენ. | D2: src/components/fleet-onboarding/fleet-application-status-screen.tsx
A3: fleetApplicationStatusScreen.applicationReference | B3: Application {reference} | C3: განაცხადი {reference} | D3: src/components/fleet-onboarding/fleet-application-status-screen.tsx
A4: fleetApplicationStatusScreen.approvedBody | B4: The company account is active and every approved vehicle can be dispatched. Assign new vehicles or drivers any time from the dispatch dashboard. | C4: კომპანიის ანგარიში აქტიურია და ყველა დამტკიცებულ ავტომობილზე შესაძლებელია დანიშვნა. ახალი ავტომობილების ან მძღოლების მიმაგრება ნებისმიერ დროს შეგიძლიათ დანიშვნის პანელიდან. | D4: src/components/fleet-onboarding/fleet-application-status-screen.tsx
A5: fleetApplicationStatusScreen.companyDetailsAndVehicles | B5: Company details and {count, plural, one {# vehicle need} other {# vehicles need}} correcting | C5: კომპანიის მონაცემები და {count} ავტომობილი საჭიროებს შესწორებას | D5: src/components/fleet-onboarding/fleet-application-status-screen.tsx
A6: fleetApplicationStatusScreen.companyDetailsNeedCorrecting | B6: Company details need correcting | C6: კომპანიის მონაცემები საჭიროებს შესწორებას | D6: src/components/fleet-onboarding/fleet-application-status-screen.tsx
A7: fleetApplicationStatusScreen.companyRegistration | B7: Company registration: | C7: კომპანიის რეგისტრაცია: | D7: src/components/fleet-onboarding/fleet-application-status-screen.tsx
A8: fleetApplicationStatusScreen.correctAFlaggedVehicle | B8: Correct a flagged vehicle | C8: მონიშნული ტრანსპორტის გასწორება | D8: src/components/fleet-onboarding/fleet-application-status-screen.tsx
A9: fleetApplicationStatusScreen.correctTheCompanyDetails | B9: Correct the company details | C9: კომპანიის დეტალების გასწორება | D9: src/components/fleet-onboarding/fleet-application-status-screen.tsx
A10: fleetApplicationStatusScreen.fix | B10: Fix | C10: გასწორება | D10: src/components/fleet-onboarding/fleet-application-status-screen.tsx
A11: fleetApplicationStatusScreen.fixCompanyDetails | B11: Fix company details | C11: კომპანიის დეტალების გასწორება | D11: src/components/fleet-onboarding/fleet-application-status-screen.tsx
A12: fleetApplicationStatusScreen.fixVehicleSr | B12: vehicle {number} | C12: ავტომობილი {number} | D12: src/components/fleet-onboarding/fleet-application-status-screen.tsx
... A214: vehicleEditorDialog.usableVolume | B214: Usable volume {volume} m³ — used to match this vehicle with orders. | C214: სასარგებლო მოცულობა {volume} მ³ — გამოიყენება ამ ავტომობილის შეკვეთებთან შესაბამისობისთვის. | D214: src/components/fleet-onboarding/vehicle-editor-dialog.tsx

Sheet home
A1: key | B1: english | C1: georgian | D1: source
A2: addCardDialog.addCard | B2: Add card | C2: ბარათის დამატება | D2: src/components/home/add-card-dialog.tsx
A3: addCardDialog.asPrintedOnTheCard | B3: As printed on the card | C3: როგორც დაბეჭდილია ბარათზე | D3: src/components/home/add-card-dialog.tsx
A4: addCardDialog.cardNumber | B4: Card number | C4: ბარათის ნომერი | D4: src/components/home/add-card-dialog.tsx
A5: addCardDialog.creditOrDebitCardNothingIs | B5: Credit or debit card. Nothing is charged until you book a delivery. | C5: საკრედიტო ან დებეტის ბარათი. თანხა არ ჩამოგეჭრებათ, სანამ მიწოდებას არ დაჯავშნით. | D5: src/components/home/add-card-dialog.tsx
A6: addCardDialog.cvc | B6: CVC | C6: CVC | D6: src/components/home/add-card-dialog.tsx
A7: addCardDialog.enterCardNumber | B7: Enter a card number of at least {min} digits. | C7: შეიყვანეთ ბარათის ნომერი, მინიმუმ {min} ციფრი. | D7: src/components/home/add-card-dialog.tsx
A8: addCardDialog.enterCvc | B8: Enter the three- or four-digit security code. | C8: შეიყვანეთ სამ- ან ოთხნიშნა უსაფრთხოების კოდი. | D8: src/components/home/add-card-dialog.tsx
A9: addCardDialog.enterExpiryFormat | B9: Enter the expiry date as MM/YY. | C9: შეიყვანეთ მოქმედების ვადა ფორმატით MM/YY. | D9: src/components/home/add-card-dialog.tsx
A10: addCardDialog.enterFutureExpiry | B10: Enter an expiry date in the future. | C10: შეიყვანეთ მომავალი თარიღის მოქმედების ვადა. | D10: src/components/home/add-card-dialog.tsx
A11: addCardDialog.enterHolderName | B11: Enter the name printed on the card. | C11: შეიყვანეთ ბარათზე დაბეჭდილი სახელი. | D11: src/components/home/add-card-dialog.tsx
A12: addCardDialog.expiry | B12: Expiry | C12: მოქმედების ვადა | D12: src/components/home/add-card-dialog.tsx
... A152: stopContactDialog.save | B152: Save | C152: შენახვა | D152: src/components/home/stop-contact-dialog.tsx

Sheet landing
A1: key | B1: english | C1: georgian | D1: source
A2: landingCategoryTiles.fromPrice | B2: from {price} | C2: {price}-დან | D2: src/components/landing/landing-category-tiles.tsx
A3: landingCategoryTiles.fromPriceEmphasised | B3: from <figure>{price}</figure> | C3: <figure>{price}</figure>-დან | D3: src/components/landing/landing-category-tiles.tsx
A4: landingCategoryTiles.priceYourOwnRoute | B4: — price your own route | C4: — გამოთვალეთ მარშრუტის ფასი | D4: src/components/landing/landing-category-tiles.tsx
A5: landingHeroCarousel.featuredBanners | B5: Featured banners | C5: რჩეული ბანერები | D5: src/components/landing/landing-hero-carousel.tsx
A6: landingHeroCarousel.goToBanner | B6: Go to banner {index} | C6: ბანერზე გადასვლა: {index} | D6: src/components/landing/landing-hero-carousel.tsx
A7: landingHeroCarousel.nextBanner | B7: Next banner | C7: შემდეგი ბანერი | D7: src/components/landing/landing-hero-carousel.tsx
A8: landingHeroCarousel.previousBanner | B8: Previous banner | C8: წინა ბანერი | D8: src/components/landing/landing-hero-carousel.tsx
A9: landingHeroCarousel.slideOf | B9: {index} of {count} | C9: {index} / {count} | D9: src/components/landing/landing-hero-carousel.tsx
A10: landingNavPill.closeMenu | B10: Close menu | C10: მენიუს დახურვა | D10: src/components/landing/landing-nav-pill.tsx
A11: landingNavPill.openMenu | B11: Open menu | C11: მენიუს გახსნა | D11: src/components/landing/landing-nav-pill.tsx
A12: landingQuoteCalculator.1IsTheDriverAloneEach | B12: 1 is the driver alone. Each extra person helps load and unload, and adds a flat fee. | C12: 1 ნიშნავს, რომ მძღოლი მარტოა. ყოველი დამატებითი ადამიანი ეხმარება დატვირთვა-დაცლაში და ემატება ფიქსირებული საფასური. | D12: src/components/landing/landing-quote-calculator.tsx
... A27: landingVehicleTypes.couldNotLoadTheVehicleTypes | B27: Could not load the vehicle types. Please refresh and try again. | C27: ავტომობილის ტიპების ჩატვირთვა ვერ მოხერხდა. განაახლეთ გვერდი და სცადეთ თავიდან. | D27: src/components/landing/landing-vehicle-types.ts

Sheet onboarding
A1: key | B1: english | C1: georgian | D1: source
A2: applicationStatusScreen.accountActivation | B2: Account activation | C2: ანგარიშის გააქტიურება | D2: src/components/driver-onboarding/application-status-screen.tsx
A3: applicationStatusScreen.allPhotosReplaced | B3: All photos replaced | C3: ყველა ფოტო ჩანაცვლებულია | D3: src/components/driver-onboarding/application-status-screen.tsx
A4: applicationStatusScreen.applicationSubmitted | B4: Application submitted | C4: განაცხადი გაგზავნილია | D4: src/components/driver-onboarding/application-status-screen.tsx
A5: applicationStatusScreen.approvedBody | B5: Your account is active. Orders matching your vehicle class will start arriving as soon as you go online. | C5: თქვენი ანგარიში აქტიურია. თქვენი ავტომობილის კლასის შესაბამისი შეკვეთები ონლაინ რეჟიმში გადასვლისთანავე დაიწყებს შემოსვლას. | D5: src/components/driver-onboarding/application-status-screen.tsx
A6: applicationStatusScreen.documentReview | B6: Document review | C6: დოკუმენტების გადამოწმება | D6: src/components/driver-onboarding/application-status-screen.tsx
A7: applicationStatusScreen.documentsNeedNewPhoto | B7: {count, plural, one {# document needs a new photo} other {# documents need a new photo}} | C7: {count, plural, one {# დოკუმენტს ახალი ფოტო სჭირდება} other {# დოკუმენტს ახალი ფოტო სჭირდება}} | D7: src/components/driver-onboarding/application-status-screen.tsx
A8: applicationStatusScreen.flaggedDocumentAlt | B8: The {document} the review team flagged | C8: {document}, რომელიც განხილვის გუნდმა მონიშნა | D8: src/components/driver-onboarding/application-status-screen.tsx
A9: applicationStatusScreen.flaggedItemsBody | B9: The review team could not read the items below. Replace them and resubmit — the rest of your application is kept. | C9: განხილვის გუნდმა ქვემოთ მოცემული ელემენტები ვერ წაიკითხა. ჩაანაცვლეთ ისინი და ხელახლა გაგზავნეთ — განაცხადის დანარჩენი ნაწილი შენახულია. | D9: src/components/driver-onboarding/application-status-screen.tsx
A10: applicationStatusScreen.goOnlineAndTakeOrders | B10: Go online and take orders | C10: ონლაინ რეჟიმში გადასვლა და შეკვეთების მიღება | D10: src/components/driver-onboarding/application-status-screen.tsx
A11: applicationStatusScreen.goOnlineFailed | B11: We couldn't set you online. Please try again. | C11: ონლაინ რეჟიმში გადაყვანა ვერ მოხერხდა. გთხოვთ, სცადოთ თავიდან. | D11: src/components/driver-onboarding/application-status-screen.tsx
A12: applicationStatusScreen.goingOnline | B12: Going online… | C12: ონლაინ რეჟიმში გადასვლა… | D12: src/components/driver-onboarding/application-status-screen.tsx
... A216: vehicleClasses.trailerTruck | B216: Trailer Truck | C216: მისაბმელიანი სატვირთო | D216: src/lib/driver-onboarding/vehicle-classes.ts

Sheet orders
A1: key | B1: english | C1: georgian | D1: source
A2: orderStatus.accepted | B2: Accepted | C2: დადასტურებული | D2: src/components/orders-format.ts
A3: orderStatus.cancelled | B3: Cancelled | C3: გაუქმებული | D3: src/components/orders-format.ts
A4: orderStatus.completed | B4: Completed | C4: დასრულებული | D4: src/components/orders-format.ts
A5: orderStatus.inTransit | B5: In transit | C5: გზაში | D5: src/components/orders-format.ts
A6: orderStatus.initiated | B6: Initiated | C6: ინიცირებული | D6: src/components/orders-format.ts
A7: orderStatus.pending | B7: Pending | C7: მოლოდინში | D7: src/components/orders-format.ts
A8: orderTrackingMap.driverLocationMayBeStale | B8: Driver location may be stale. | C8: მძღოლის მდებარეობა შესაძლოა მოძველებული იყოს | D8: src/components/order-tracking-map.tsx
A9: orderTrackingMap.waitingForADriverToShare | B9: Waiting for a driver to share their location… | C9: ველოდებით მძღოლის მიერ მდებარეობის გაზიარებას... | D9: src/components/order-tracking-map.tsx
A10: orders.above | B10: above. | C10: ზემოთ. | D10: src/app/[locale]/orders/page.tsx
A11: orders.bookFirstDelivery | B11: Book your first delivery with <b>New order</b> above. | C11: პირველი მიწოდება დაჯავშნეთ ზემოთ მოცემული ღილაკით <b>ახალი შეკვეთა</b>. | D11: src/app/[locale]/orders/page.tsx
A12: orders.newOrder2 | B12: New order | C12: ახალი შეკვეთა | D12: src/app/[locale]/orders/page.tsx
... A25: serviceLevel.regular | B25: Regular | C25: სტანდარტული | D25: src/components/orders-format.ts

Sheet wallet
A1: key | B1: english | C1: georgian | D1: source
A2: savedCardsPanel.armedDefaultNote | B2: Click again to remove this card for good. There is no undo, and your next card becomes the default. | C2: დააჭირეთ ხელახლა ბარათის სამუდამოდ წასაშლელად. ამის გაუქმება შეუძლებელია და ნაგულისხმევი გახდება თქვენი შემდეგი ბარათი. | D2: src/components/wallet/saved-cards-panel.tsx
A3: savedCardsPanel.armedNote | B3: Click again to remove this card for good. There is no undo. | C3: დააჭირეთ ხელახლა ბარათის სამუდამოდ წასაშლელად. ამის გაუქმება შეუძლებელია. | D3: src/components/wallet/saved-cards-panel.tsx
A4: savedCardsPanel.cancelRemovalAria | B4: Cancel removal, {card} | C4: წაშლის გაუქმება, {card} | D4: src/components/wallet/saved-cards-panel.tsx
A5: savedCardsPanel.cardDescription | B5: {brand} card ending {last4} | C5: {brand} ბარათი, ბოლო ციფრები {last4} | D5: src/components/wallet/saved-cards-panel.tsx
A6: savedCardsPanel.confirmRemoval | B6: Confirm removal | C6: წაშლის დადასტურება | D6: src/components/wallet/saved-cards-panel.tsx
A7: savedCardsPanel.confirmRemovalAria | B7: Confirm removal, {card} | C7: წაშლის დადასტურება, {card} | D7: src/components/wallet/saved-cards-panel.tsx
A8: savedCardsPanel.default | B8: Default | C8: ნაგულისხმევი | D8: src/components/wallet/saved-cards-panel.tsx
A9: savedCardsPanel.defaultFailed | B9: Could not make this card your default. | C9: ბარათის ნაგულისხმევად დაყენება ვერ მოხერხდა. | D9: src/components/wallet/saved-cards-panel.tsx
A10: savedCardsPanel.makeDefault | B10: Make default | C10: ნაგულისხმევად დაყენება | D10: src/components/wallet/saved-cards-panel.tsx
A11: savedCardsPanel.makeDefaultAria | B11: Make default, {card} | C11: ნაგულისხმევად დაყენება, {card} | D11: src/components/wallet/saved-cards-panel.tsx
A12: savedCardsPanel.networkError | B12: Network error. Check your connection and try again. | C12: ქსელის შეცდომა. შეამოწმეთ კავშირი და სცადეთ ხელახლა. | D12: src/components/wallet/saved-cards-panel.tsx
... A21: wallet.pleaseSignInToViewYour | B21: Please sign in to view your wallet. | C21: თქვენი საფულის სანახავად, გთხოვთ, გაიაროთ ავტორიზაცია. | D21: src/app/[locale]/wallet/page.tsx
